bluestacks5newinstances/README.MD
bluestacks5newinstances/__init__.py
bluestacks5newinstances/requirements.txt
bluestacks5newinstances/thirdparty.json
bluestacks5newinstances-0.10.dist-info/LICENSE.rst
bluestacks5newinstances-0.10.dist-info/METADATA
bluestacks5newinstances-0.10.dist-info/WHEEL
bluestacks5newinstances-0.10.dist-info/top_level.txt
bluestacks5newinstances-0.10.dist-info/RECORD
