Metadata-Version: 2.1
Name: bluestacks5newinstances
Version: 0.10
Summary: Creates multiple instances of BlueStacks 5 with an independent system disk.
Home-page: https://github.com/hansalemaos/bluestacks5newinstances
Author: Johannes Fischer
Author-email: aulasparticularesdealemaosp@gmail.com
License: MIT
Keywords: BlueStacks,instance
Classifier: Development Status :: 4 - Beta
Classifier: Programming Language :: Python :: 3 :: Only
Classifier: Programming Language :: Python :: 3.10
Classifier: Topic :: Software Development :: Libraries :: Python Modules
Classifier: Topic :: Utilities
License-File: LICENSE.rst
Requires-Dist: consolectrlchandler
Requires-Dist: exceptdrucker
Requires-Dist: flatten-any-dict-iterable-or-whatsoever
Requires-Dist: killallappsinfolder
Requires-Dist: list-all-files-recursively-short
Requires-Dist: reggisearch
Requires-Dist: rootstacks
Requires-Dist: xmltodict
